[
  {
    "title": "요즘 10대 에이블리 최애템은..이거래여🙊",
    "video_url": "https://www.youtube.com/watch?v=S5FFFlqxpFU",
    "avg_cb_score": 0.149,
    "spike_dates": [
      "2025-03-11T00:00:00",
      "2025-03-15T00:00:00"
    ],
    "high_risk_dates": [
      "2025-03-11T00:00:00",
      "2025-03-15T00:00:00",
      "2025-03-18T00:00:00"
    ],
    "risk_zone": {
      "start_date": "2025-03-11T00:00:00",
      "end_date": "2025-03-18T00:00:00"
    },
    "cb_score_trend": [
      {
        "date": "2025-03-09T00:00:00",
        "cb_score": 0.03
      },
      {
        "date": "2025-03-10T00:00:00",
        "cb_score": 0.11
      },
      {
        "date": "2025-03-11T00:00:00",
        "cb_score": 0.5
      },
      {
        "date": "2025-03-12T00:00:00",
        "cb_score": 0.07
      },
      {
        "date": "2025-03-13T00:00:00",
        "cb_score": 0.0
      },
      {
        "date": "2025-03-14T00:00:00",
        "cb_score": 0.0
      },
      {
        "date": "2025-03-15T00:00:00",
        "cb_score": 0.25
      },
      {
        "date": "2025-03-16T00:00:00",
        "cb_score": 0.2
      },
      {
        "date": "2025-03-17T00:00:00",
        "cb_score": 0.2
      },
      {
        "date": "2025-03-18T00:00:00",
        "cb_score": 0.28
      },
      {
        "date": "2025-03-26T00:00:00",
        "cb_score": 0.0
      }
    ],
    "emotion_ratio": {
      "행복": 0.407,
      "공포": 0.259,
      "중립": 0.111,
      "놀람": 0.111,
      "분노": 0.074,
      "혐오": 0.037
    },
    "topic_ratio": {
      "정보 / 꿀팁": 0.296,
      "공감 / 감정 공유": 0.185,
      "제품 / 아이템 리뷰": 0.148,
      "기타 / 미분류": 0.148,
      "질문 / 피드백": 0.111,
      "사건 / 논란": 0.037,
      "콘텐츠 평가": 0.037,
      "유머 / 드립": 0.037
    },
    "cluster_ratio": {
      "Neutral Informative": 0.259,
      "Supportive": 0.259,
      "Aggressive": 0.185,
      "Sarcastic/Playful": 0.148,
      "Fear": 0.074,
      "Anger": 0.037,
      "Analytical": 0.037
    },
    "tfidf_keywords": [
      "gingxnet랄지똥을싸라니도치마입어그럼",
      "가디건도",
      "가디건은",
      "같은데",
      "궁금해요",
      "그거",
      "그런걸",
      "그런듯",
      "근데",
      "금지해야",
      "길어보여요",
      "껀데",
      "남자바지는",
      "누가시키는거야",
      "다리가"
    ],
    "freq_keywords": [
      "그거",
      "혹시",
      "어느",
      "정도가",
      "입을",
      "잇을까요",
      "저런거랑",
      "비슷한",
      "남자바지는",
      "없으려나",
      "바지는",
      "법으로",
      "금지해야",
      "당연하죠",
      "근데"
    ],
    "summary": "2025-03-11T00:00:00~2025-03-18T00:00:00 동안 CB Score가 평균보다 높거나 급등했습니다. 주요 감정은 '행복', 주제는 '정보 / 꿀팁', 댓글 유형은 'Neutral Informative'가 많았습니다.",
    "aggressive_comments": [
      {
        "date": "2025-03-09",
        "emotion": "공포",
        "topic": "질문 / 피드백",
        "cluster": "Aggressive",
        "text": "근데 이렇게 리뷰하려고샀다가 맘에안드시면 다시파시나요? 궁금쓰.."
      },
      {
        "date": "2025-03-10",
        "emotion": "분노",
        "topic": "사건 / 논란",
        "cluster": "Aggressive",
        "text": "시러..."
      },
      {
        "date": "2025-03-11",
        "emotion": "공포",
        "topic": "정보 / 꿀팁",
        "cluster": "Aggressive",
        "text": "언니가 입으신 셔츠랑 가디건도 정보 궁금해요!!그런걸 찾고있는대 알려주세요ㅠㅠㅠ"
      },
      {
        "date": "2025-03-12",
        "emotion": "공포",
        "topic": "정보 / 꿀팁",
        "cluster": "Aggressive",
        "text": "마자요 가디건은 제너럴아이디어꺼구<br>셔츠는 일리고 껀데 이름이 무슨 보헤미안 ..?어쩌고 셔츠였던것 같은데…🤔"
      },
      {
        "date": "2025-03-15",
        "emotion": "공포",
        "topic": "제품 / 아이템 리뷰",
        "cluster": "Aggressive",
        "text": "이거 슈가파우더 제품중에 저거 와이드 조절 안돼는게 있는데 그거 인기가 많긴한데 저는 비추해요… 그거 엉덩이 쪽 핏이 좀.. 이상해요"
      },
      {
        "date": "2025-03-18",
        "emotion": "분노",
        "topic": "기타 / 미분류",
        "cluster": "Aggressive",
        "text": "@@gingxnet랄지똥을싸라니도치마입어그럼"
      }
    ]
  },
  {
    "title": "쿠팡 1만 원대 다이슨 에어랩..신기한데?🙊🌪️",
    "video_url": "https://www.youtube.com/watch?v=tZ-gyb-Klgg",
    "avg_cb_score": 0.112,
    "spike_dates": [
      "2025-03-29T00:00:00"
    ],
    "high_risk_dates": [
      "2025-03-29T00:00:00"
    ],
    "risk_zone": {
      "start_date": "2025-03-29T00:00:00",
      "end_date": "2025-03-29T00:00:00"
    },
    "cb_score_trend": [
      {
        "date": "2025-03-16T00:00:00",
        "cb_score": 0.04
      },
      {
        "date": "2025-03-17T00:00:00",
        "cb_score": 0.0
      },
      {
        "date": "2025-03-24T00:00:00",
        "cb_score": 0.0
      },
      {
        "date": "2025-03-25T00:00:00",
        "cb_score": 0.02
      },
      {
        "date": "2025-03-29T00:00:00",
        "cb_score": 0.5
      }
    ],
    "emotion_ratio": {
      "공포": 1.0
    },
    "topic_ratio": {
      "기타 / 미분류": 1.0
    },
    "cluster_ratio": {
      "Aggressive": 1.0
    },
    "tfidf_keywords": [
      "가져와야하나",
      "다시",
      "버리고왔는데",
      "사고",
      "안돼서",
      "이거",
      "할아버지댁에"
    ],
    "freq_keywords": [
      "이거",
      "사고",
      "안돼서",
      "할아버지댁에",
      "버리고왔는데",
      "다시",
      "가져와야하나"
    ],
    "summary": "2025-03-29T00:00:00~2025-03-29T00:00:00 동안 CB Score가 평균보다 높거나 급등했습니다. 주요 감정은 '공포', 주제는 '기타 / 미분류', 댓글 유형은 'Aggressive'가 많았습니다.",
    "aggressive_comments": [
      {
        "date": "2025-03-16",
        "emotion": "공포",
        "topic": "사건 / 논란",
        "cluster": "Aggressive",
        "text": "이거 사지마여,,,"
      },
      {
        "date": "2025-03-29",
        "emotion": "공포",
        "topic": "기타 / 미분류",
        "cluster": "Aggressive",
        "text": "이거 사고 안돼서 할아버지댁에 버리고왔는데 다시 가져와야하나"
      }
    ]
  },
  {
    "title": "25년 떡상할!확~바뀐 신발 트렌드👟",
    "video_url": "https://www.youtube.com/watch?v=YPkcNpHuC5Q",
    "avg_cb_score": 0.087,
    "spike_dates": [
      "2025-04-19T00:00:00",
      "2025-04-21T00:00:00"
    ],
    "high_risk_dates": [
      "2025-04-19T00:00:00",
      "2025-04-20T00:00:00",
      "2025-04-21T00:00:00"
    ],
    "risk_zone": {
      "start_date": "2025-04-19T00:00:00",
      "end_date": "2025-04-21T00:00:00"
    },
    "cb_score_trend": [
      {
        "date": "2025-04-08T00:00:00",
        "cb_score": 0.03
      },
      {
        "date": "2025-04-09T00:00:00",
        "cb_score": 0.05
      },
      {
        "date": "2025-04-10T00:00:00",
        "cb_score": 0.08
      },
      {
        "date": "2025-04-11T00:00:00",
        "cb_score": 0.05
      },
      {
        "date": "2025-04-12T00:00:00",
        "cb_score": 0.1
      },
      {
        "date": "2025-04-13T00:00:00",
        "cb_score": 0.01
      },
      {
        "date": "2025-04-14T00:00:00",
        "cb_score": 0.06
      },
      {
        "date": "2025-04-15T00:00:00",
        "cb_score": 0.07
      },
      {
        "date": "2025-04-16T00:00:00",
        "cb_score": 0.03
      },
      {
        "date": "2025-04-17T00:00:00",
        "cb_score": 0.0
      },
      {
        "date": "2025-04-18T00:00:00",
        "cb_score": 0.0
      },
      {
        "date": "2025-04-19T00:00:00",
        "cb_score": 0.2
      },
      {
        "date": "2025-04-20T00:00:00",
        "cb_score": 0.25
      },
      {
        "date": "2025-04-21T00:00:00",
        "cb_score": 0.55
      },
      {
        "date": "2025-04-23T00:00:00",
        "cb_score": 0.13
      },
      {
        "date": "2025-04-24T00:00:00",
        "cb_score": 0.0
      },
      {
        "date": "2025-04-25T00:00:00",
        "cb_score": 0.0
      },
      {
        "date": "2025-04-26T00:00:00",
        "cb_score": 0.0
      },
      {
        "date": "2025-04-28T00:00:00",
        "cb_score": 0.07
      },
      {
        "date": "2025-04-29T00:00:00",
        "cb_score": 0.05
      }
    ],
    "emotion_ratio": {
      "혐오": 0.286,
      "분노": 0.286,
      "행복": 0.286,
      "놀람": 0.143
    },
    "topic_ratio": {
      "사건 / 논란": 0.429,
      "정보 / 꿀팁": 0.286,
      "제품 / 아이템 리뷰": 0.143,
      "사회 / 시사 이슈": 0.143
    },
    "cluster_ratio": {
      "Aggressive": 0.571,
      "Supportive": 0.286,
      "Neutral Informative": 0.143
    },
    "tfidf_keywords": [
      "개짝은",
      "나는",
      "납작해져가는것이야",
      "내는",
      "다시",
      "만들더니만",
      "못신어",
      "빠방해서",
      "신발들",
      "싫어",
      "아프다고",
      "어글리",
      "유발",
      "유행해죠",
      "작살"
    ],
    "freq_keywords": [
      "다시",
      "아프다고",
      "폭신하게",
      "쿠션",
      "빠방해서",
      "만들더니만",
      "짚신처럼",
      "납작해져가는것이야",
      "개짝은",
      "나는",
      "저런거",
      "싫어",
      "못신어",
      "어글리",
      "유행해죠"
    ],
    "summary": "2025-04-19T00:00:00~2025-04-21T00:00:00 동안 CB Score가 평균보다 높거나 급등했습니다. 주요 감정은 '혐오', 주제는 '사건 / 논란', 댓글 유형은 'Aggressive'가 많았습니다.",
    "aggressive_comments": [
      {
        "date": "2025-04-08",
        "emotion": "혐오",
        "topic": "제품 / 아이템 리뷰",
        "cluster": "Aggressive",
        "text": "아디레이서... 살면서 신어본 신발중애 가장 불편"
      },
      {
        "date": "2025-04-08",
        "emotion": "혐오",
        "topic": "사건 / 논란",
        "cluster": "Aggressive",
        "text": "사실상 저런거 신는사람 1%미만이라 그냥 유행도 아니고 그냥 그들만의 리그임"
      },
      {
        "date": "2025-04-09",
        "emotion": "혐오",
        "topic": "질문 / 피드백",
        "cluster": "Aggressive",
        "text": "언제까지 스피드캣 신을거에요?"
      },
      {
        "date": "2025-04-09",
        "emotion": "혐오",
        "topic": "제품 / 아이템 리뷰",
        "cluster": "Aggressive",
        "text": "올해는 걍 에어포스1 신자 ㅈ망이네"
      },
      {
        "date": "2025-04-10",
        "emotion": "분노",
        "topic": "기타 / 미분류",
        "cluster": "Aggressive",
        "text": "키 5센치는 담당했던 운둥화들을 포기하고 내려오라고??<br>앙대!!! 내 기럭지 지켜야 됨"
      },
      {
        "date": "2025-04-10",
        "emotion": "혐오",
        "topic": "사건 / 논란",
        "cluster": "Aggressive",
        "text": "조선 나이키"
      },
      {
        "date": "2025-04-11",
        "emotion": "혐오",
        "topic": "사회 / 시사 이슈",
        "cluster": "Aggressive",
        "text": "주구장창 호카 온라닝만 신나.. 여기무슨 난달라!하면서 패션영상에 발편한게짱이지 쓰는사람들은 어디서 칭찬못받고 삶?"
      },
      {
        "date": "2025-04-11",
        "emotion": "혐오",
        "topic": "사회 / 시사 이슈",
        "cluster": "Aggressive",
        "text": "ㅋㅋㅋㅋ 그냥 집에 있는 운동화 신으세요~<br>경제불황에 신발 구매는 사치입니다!"
      },
      {
        "date": "2025-04-19",
        "emotion": "분노",
        "topic": "사건 / 논란",
        "cluster": "Aggressive",
        "text": "발 작살 내는 신발들"
      },
      {
        "date": "2025-04-20",
        "emotion": "혐오",
        "topic": "제품 / 아이템 리뷰",
        "cluster": "Aggressive",
        "text": "발 아프다고 폭신하게 쿠션 빠방해서 만들더니만 왜 다시 짚신처럼 납작해져가는것이야....."
      },
      {
        "date": "2025-04-21",
        "emotion": "혐오",
        "topic": "사건 / 논란",
        "cluster": "Aggressive",
        "text": "키 개짝은 나는.....저런거...싫어....못신어 ㅠㅠㅠㅠ 어글리 다시 유행해죠..."
      },
      {
        "date": "2025-04-21",
        "emotion": "분노",
        "topic": "사건 / 논란",
        "cluster": "Aggressive",
        "text": "족저근막염 유발"
      },
      {
        "date": "2025-04-23",
        "emotion": "혐오",
        "topic": "사회 / 시사 이슈",
        "cluster": "Aggressive",
        "text": "ㄹㅇ사람들 다른사람한테 진짜 관심없음ㅋㅋㅋ오늘하루 본 사람 신은 신발5개만 말해라 해도 모를걸, 본인편한거 사세요"
      }
    ]
  }
]